pocketx/__init__.py
pocketx/account.py
pocketx/base.py
pocketx/constant.py
pocketx/contracts.py
pocketx/data.py
pocketx/error.py
pocketx/order.py
pocketx/pocketx.py
pocketx/position.py
pocketx/TWCASignDLL/TWCASignDLL_64.dll
pocketx/TWCASignDLL/TwcaSignDLL.py
pocketx/TWCASignDLL/__init__.py
pocketx/TWCASignDLL/libeay32MD.dll
pocketx/TWCASignDLL/p7Sign.properties
pocketx/backend/__init__.py
pocketx/backend/utils.cpython-39-darwin.so
pocketx-0.0.3.dist-info/METADATA
pocketx-0.0.3.dist-info/WHEEL
pocketx-0.0.3.dist-info/top_level.txt
pocketx-0.0.3.dist-info/RECORD
