Metadata-Version: 2.4
Name: pocketx
Version: 0.0.3
Summary: Pocket Security Trading Api
Author-email: FelixChih <felix6258925@gmail.com>
License: MIT
Keywords: pocket,pocket-sdk,pocket_sdk,pocket-api,pocket_api
Classifier: Programming Language :: Python :: 3
Classifier: Operating System :: Microsoft :: Windows
Classifier: Operating System :: MacOS :: MacOS X
Classifier: Operating System :: POSIX :: Linux
Requires-Python: >=3.7
Requires-Dist: requests>=2.31.0
Requires-Dist: pydantic>=2.9.1
Requires-Dist: pulsar-client>=3.5.0
Requires-Dist: pandas<3.0,>=2.0.3
Requires-Dist: numpy>=1.24.4
Requires-Dist: aiohttp>=3.10.8
Requires-Dist: importlib_metadata>=8.4.0
